nonebot_plugin_multincm/__init__.py
nonebot_plugin_multincm/config.py
nonebot_plugin_multincm/const.py
nonebot_plugin_multincm/data_source/__init__.py
nonebot_plugin_multincm/data_source/album.py
nonebot_plugin_multincm/data_source/base.py
nonebot_plugin_multincm/data_source/playlist.py
nonebot_plugin_multincm/data_source/program.py
nonebot_plugin_multincm/data_source/radio.py
nonebot_plugin_multincm/data_source/song.py
nonebot_plugin_multincm/data_source/raw/__init__.py
nonebot_plugin_multincm/data_source/raw/login.py
nonebot_plugin_multincm/data_source/raw/models.py
nonebot_plugin_multincm/data_source/raw/request.py
nonebot_plugin_multincm/interaction/__init__.py
nonebot_plugin_multincm/interaction/cache.py
nonebot_plugin_multincm/interaction/resolver.py
nonebot_plugin_multincm/interaction/commands/__init__.py
nonebot_plugin_multincm/interaction/commands/direct.py
nonebot_plugin_multincm/interaction/commands/lyric.py
nonebot_plugin_multincm/interaction/commands/resolve.py
nonebot_plugin_multincm/interaction/commands/search.py
nonebot_plugin_multincm/interaction/commands/upload.py
nonebot_plugin_multincm/interaction/message/__init__.py
nonebot_plugin_multincm/interaction/message/common.py
nonebot_plugin_multincm/interaction/message/song_card.py
nonebot_plugin_multincm/interaction/message/song_file.py
nonebot_plugin_multincm/render/__init__.py
nonebot_plugin_multincm/render/card_list.py
nonebot_plugin_multincm/render/lyrics.py
nonebot_plugin_multincm/render/utils.py
nonebot_plugin_multincm/render/templates/base.html.jinja
nonebot_plugin_multincm/render/templates/card_list.html.jinja
nonebot_plugin_multincm/render/templates/lyrics.html.jinja
nonebot_plugin_multincm/render/templates/track_card.html.jinja
nonebot_plugin_multincm/utils/__init__.py
nonebot_plugin_multincm/utils/base.py
nonebot_plugin_multincm/utils/lrc_parser.py
nonebot_plugin_multincm-1.2.8.dist-info/METADATA
nonebot_plugin_multincm-1.2.8.dist-info/WHEEL
nonebot_plugin_multincm-1.2.8.dist-info/licenses/LICENSE
nonebot_plugin_multincm-1.2.8.dist-info/RECORD
