Metadata-Version: 2.4
Name: nonebot-plugin-multincm
Version: 1.2.8
Summary: NCM Song Searcher
Project-URL: homepage, https://github.com/lgc-NB2Dev/nonebot-plugin-multincm
Author-email: LgCookie <lgc2333@126.com>
License: MIT
License-File: LICENSE
Requires-Python: <4.0,>=3.10
Requires-Dist: cachetools>=6.1.0
Requires-Dist: cookit[jinja,loguru,nonebot-alconna,nonebot-localstore,pydantic]>=0.13.2
Requires-Dist: httpx>=0.28.1
Requires-Dist: jinja2>=3.1.5
Requires-Dist: nonebot-plugin-alconna>=0.59.4
Requires-Dist: nonebot-plugin-htmlrender>=0.6.6
Requires-Dist: nonebot-plugin-localstore>=0.7.4
Requires-Dist: nonebot-plugin-waiter>=0.8.1
Requires-Dist: nonebot2>=2.4.3
Requires-Dist: pyncm>=1.7.1
Requires-Dist: qrcode>=8.2
Requires-Dist: silk-python>=0.2.7
Requires-Dist: typing-extensions>=4.14.1
Requires-Dist: yarl>=1.20.1
